adc_aiopg/__init__.py
adc_aiopg/alembic_env.py
adc_aiopg/connection.py
adc_aiopg/enum.py
adc_aiopg/errors.py
adc_aiopg/py.typed
adc_aiopg/query.py
adc_aiopg/types.py
adc_aiopg/version_table.py
adc_aiopg/repository/__init__.py
adc_aiopg/repository/dao.py
adc_aiopg/repository/db_repository.py
adc_aiopg/repository/entity_db_repository.py
adc_aiopg-0.1.0.dist-info/licenses/LICENSE
adc_aiopg-0.1.0.dist-info/METADATA
adc_aiopg-0.1.0.dist-info/WHEEL
adc_aiopg-0.1.0.dist-info/top_level.txt
adc_aiopg-0.1.0.dist-info/RECORD
