Metadata-Version: 2.4
Name: adc-aiopg
Version: 0.1.0
Summary: Async PostgreSQL client with connection pooling
Home-page: https://github.com/ascet-dev/adc-aiopg
License: MIT
Classifier: Development Status :: 4 - Beta
Classifier: Intended Audience :: Developers
Classifier: License :: OSI Approved :: MIT License
Classifier: Programming Language :: Python :: 3
Classifier: Programming Language :: Python :: 3.8
Classifier: Programming Language :: Python :: 3.9
Classifier: Programming Language :: Python :: 3.10
Classifier: Programming Language :: Python :: 3.11
Classifier: Topic :: Database
Classifier: Topic :: Database :: Database Engines/Servers
Classifier: Topic :: Software Development :: Libraries :: Python Modules
Requires-Python: >=3.8
License-File: LICENSE
Requires-Dist: pydantic>=2.0.0
Requires-Dist: asyncpg>=0.27.0
Requires-Dist: alembic>=1.11.0
Requires-Dist: sqlalchemy>=2.0.0
Requires-Dist: sqlmodel>=0.0.8
Requires-Dist: ujson>=5.10.0
Requires-Dist: psycopg2-binary>=2.9.0
Requires-Dist: sqlalchemy-utils>=0.41.0
Dynamic: classifier
Dynamic: description
Dynamic: description-content-type
Dynamic: home-page
Dynamic: license
Dynamic: license-file
Dynamic: requires-dist
Dynamic: requires-python
Dynamic: summary
